{
    "pools": [
      {
        "rolls": 1,
        "entries": [
          {
            "type": "minecraft:item",
            "name": "minecraft:shield",
            "functions": [
              {
                "function": "minecraft:set_nbt",
                "tag": "{BlockEntityTag:{Base:8,Patterns:[{Color:15,Pattern:\"sku\"}],id:\"minecraft:banner\"},Damage:0,RepairCost:40,HideFlags:127}"
              },
              {
                "function": "minecraft:set_lore",
                "entity": "this",
                "lore": [
                  {
                    "text": "MOB:スケルトン",
                    "italic": false
                  },
                  {
                    "text": "※エンチャントを付与するとクラフトができなくなります！",
                    "color": "red",
                    "italic": false
                  }
                ]
              },
              {
                "function": "minecraft:set_name",
                "entity": "this",
                "name": {
                  "text": "アリーナ討伐の称号",
                  "color": "gold",
                  "italic": false,
                  "bold": true
                }
              }
            ]
          }
        ]
      }
    ]
  }
  